sinyi_utils/__init__.py
sinyi_utils/format_tool.py
sinyi_utils/sinyi.py
sinyi_utils-0.0.2.dist-info/METADATA
sinyi_utils-0.0.2.dist-info/WHEEL
sinyi_utils-0.0.2.dist-info/top_level.txt
sinyi_utils-0.0.2.dist-info/RECORD
