Metadata-Version: 2.1
Name: sinyi-utils
Version: 0.0.2
Summary: Utilities for data analysis
Home-page: https://SinyiDataTeam@dev.azure.com/SinyiDataTeam/Label360/_git/sinyi_utils
Author: sinyidatateam
Author-email: me30@sinyi.com.tw
License: MIT
Requires-Python: >=3.8
